Metadata-Version: 1.0
Name: spark-stratifier
Version: 0.1.5
Summary: Stratified Cross Validator for Spark
Home-page: https://github.com/interviewstreet/spark-stratifier
Author: Justin Suen
Author-email: justin.suen@hackerrank.com
License: MIT
Platform: UNKNOWN
